{
  "name": "",
  "serverHost": "localhost",
  "serverPort": 8989,
  "serverApiKey": "b01b28f476d86a4f427a43ed6f14fecc11a02d2e019dfad5ec1a59903a9c25d8",
  "frameHost": "localhost",
  "framePort": 8787,
  "frameAccessKey": "",
  "frameAccess": "public",
  "orgId": "bla",
  "batchId": "",
  "deviceId": "37348D3AE4D2DB29457E0F27E7EEF357",
  "width": 800,
  "height": 480,
  "metricsInterval": 60.0,
  "rotate": 0,
  "scalingMode": "cover",
  "assetsPath": "./tmp",
  "logToFile": "./tmp/frameos.log",
  "debug": true,
  "timeZone": "Europe/Brussels",
  "network": {
    "networkCheck": true,
    "networkCheckTimeoutSeconds": 30.0,
    "networkCheckUrl": "https://networkcheck.frameos.net/",
    "wifiHotspot": "disabled",
    "wifiHotspotSsid": "FrameOS",
    "wifiHotspotPassword": "frame1234",
    "wifiHotspotTimeoutSeconds": 600.0
  }
}
