{
  "edges": [
    {
      "id": "a9bf1ea8-137d-4ba0-92d0-7fd3322fea1e",
      "source": "a9bf1ea8-137d-4ba0-92d0-7fd3322fea1e",
      "sourceHandle": "fieldOutput",
      "target": "7bae8fb3-f31c-4966-ab75-3b77fba06f79",
      "targetHandle": "fieldInput/text",
      "type": "codeNodeEdge"
    },
    {
      "id": "e981d9ce-22ca-4994-9319-d36d1b996938",
      "source": "463556ab-e4fe-40c7-93f3-40bc723f454e",
      "sourceHandle": "next",
      "target": "22c56bc9-8e12-4f0a-a0cd-77fec8f96870",
      "targetHandle": "prev",
      "type": "appNodeEdge"
    },
    {
      "id": "442dbbf5-0898-44e7-9f05-448ea1d16f83",
      "source": "442dbbf5-0898-44e7-9f05-448ea1d16f83",
      "sourceHandle": "fieldOutput",
      "target": "22c56bc9-8e12-4f0a-a0cd-77fec8f96870",
      "targetHandle": "fieldInput/text",
      "type": "codeNodeEdge"
    },
    {
      "id": "155dc053-52ad-42a6-97de-2b63b8191dd7",
      "source": "155dc053-52ad-42a6-97de-2b63b8191dd7",
      "sourceHandle": "fieldOutput",
      "target": "a9bf1ea8-137d-4ba0-92d0-7fd3322fea1e",
      "targetHandle": "codeField/stars",
      "type": "codeNodeEdge"
    },
    {
      "id": "6a8737d8-ad96-4525-9302-210f89af2a0e",
      "source": "22c56bc9-8e12-4f0a-a0cd-77fec8f96870",
      "sourceHandle": "next",
      "target": "7bae8fb3-f31c-4966-ab75-3b77fba06f79",
      "targetHandle": "prev",
      "type": "appNodeEdge"
    },
    {
      "id": "232228bb-254a-480e-ac55-06cc82f11d47",
      "target": "155dc053-52ad-42a6-97de-2b63b8191dd7",
      "targetHandle": "codeField/arg",
      "source": "0b68fe3f-bcec-4b99-aebf-daf0e7fe57d8",
      "sourceHandle": "fieldOutput",
      "type": "codeNodeEdge"
    }
  ],
  "fields": [
    {
      "access": "public",
      "label": "Repository",
      "name": "repository",
      "persist": "disk",
      "placeholder": "user/repo",
      "type": "string",
      "value": "FrameOS/frameos"
    },
    {
      "access": "private",
      "label": "Stars",
      "name": "stars",
      "persist": "disk",
      "type": "integer",
      "value": "420"
    }
  ],
  "id": "427280c2-ed88-4ca5-a148-44370c8f06fb",
  "name": "Github Stars",
  "nodes": [
    {
      "data": {
        "keyword": "render"
      },
      "dragging": false,
      "height": 96,
      "id": "463556ab-e4fe-40c7-93f3-40bc723f454e",
      "position": {
        "x": 406.49647892953215,
        "y": 45.92601433901413
      },
      "positionAbsolute": {
        "x": 406.49647892953215,
        "y": 45.92601433901413
      },
      "selected": false,
      "type": "event",
      "width": 183
    },
    {
      "data": {
        "config": {},
        "keyword": "text"
      },
      "dragging": false,
      "height": 336,
      "id": "7bae8fb3-f31c-4966-ab75-3b77fba06f79",
      "position": {
        "x": 1211.9276375806458,
        "y": 72.21705598804891
      },
      "positionAbsolute": {
        "x": 1211.9276375806458,
        "y": 72.21705598804891
      },
      "selected": false,
      "type": "app",
      "width": 294
    },
    {
      "data": {
        "code": "if stars >= 0: $stars & \" star\" & (if stars == 1: \"\" else: \"s\") else: \"Error fetching stars\"",
        "codeFields": [
          "stars",
          "arg"
        ]
      },
      "dragging": false,
      "height": 155,
      "id": "a9bf1ea8-137d-4ba0-92d0-7fd3322fea1e",
      "position": {
        "x": 1212.7101897900725,
        "y": -172.25042778391318
      },
      "positionAbsolute": {
        "x": 1212.7101897900725,
        "y": -172.25042778391318
      },
      "resizing": false,
      "selected": false,
      "style": {
        "height": 155,
        "width": 505
      },
      "type": "code",
      "width": 505
    },
    {
      "data": {
        "config": {
          "fontSize": "16",
          "position": "top-left"
        },
        "keyword": "text"
      },
      "dragging": false,
      "height": 336,
      "id": "22c56bc9-8e12-4f0a-a0cd-77fec8f96870",
      "position": {
        "x": 761.7126221224416,
        "y": 57.46808474863823
      },
      "positionAbsolute": {
        "x": 761.7126221224416,
        "y": 57.46808474863823
      },
      "selected": false,
      "type": "app",
      "width": 294
    },
    {
      "data": {
        "code": "state{\"repository\"}.getStr()"
      },
      "dragging": false,
      "height": 130,
      "id": "442dbbf5-0898-44e7-9f05-448ea1d16f83",
      "position": {
        "x": 663.0518223727762,
        "y": -182.9252635128297
      },
      "positionAbsolute": {
        "x": 663.0518223727762,
        "y": -182.9252635128297
      },
      "resizing": false,
      "selected": false,
      "style": {
        "height": 130,
        "width": 304
      },
      "type": "code",
      "width": 304
    },
    {
      "data": {
        "code": "arg.getInt()",
        "codeFields": [
          "arg"
        ]
      },
      "dragging": false,
      "height": 130,
      "id": "155dc053-52ad-42a6-97de-2b63b8191dd7",
      "position": {
        "x": 1175.590605360396,
        "y": -389.32589520181864
      },
      "positionAbsolute": {
        "x": 1175.590605360396,
        "y": -389.32589520181864
      },
      "resizing": false,
      "selected": false,
      "style": {
        "height": 130,
        "width": 290
      },
      "type": "code",
      "width": 290
    },
    {
      "id": "0b68fe3f-bcec-4b99-aebf-daf0e7fe57d8",
      "position": {
        "x": 1105.0143842936616,
        "y": -535.450608370544
      },
      "type": "code",
      "data": {
        "code": "state{\"stars\"}",
        "codeFields": []
      },
      "style": {
        "width": 300,
        "height": 130
      },
      "width": 300,
      "height": 130,
      "selected": false
    }
  ],
  "settings": {
    "backgroundColor": "#000000",
    "refreshInterval": 60
  }
}